pymmcore_midi/__init__.py
pymmcore_midi/_core_connect.py
pymmcore_midi/_device.py
pymmcore_midi/_map_spec.py
pymmcore_midi/_xtouch.py
pymmcore_midi/py.typed
pymmcore_midi-0.1.0.dist-info/METADATA
pymmcore_midi-0.1.0.dist-info/WHEEL
pymmcore_midi-0.1.0.dist-info/licenses/LICENSE
pymmcore_midi-0.1.0.dist-info/RECORD
