Metadata-Version: 2.1
Name: pymmcore-midi
Version: 0.1.0
Summary: Midi control for microscopes using pymmcore
Project-URL: homepage, https://github.com/pymmcore-plus/pymmcore-midi
Project-URL: repository, https://github.com/pymmcore-plus/pymmcore-midi
Author-email: Talley Lambert <talley.lambert@gmail.com>
License: BSD-3-Clause
License-File: LICENSE
Classifier: Development Status :: 3 - Alpha
Classifier: License :: OSI Approved :: BSD License
Classifier: Programming Language :: Python :: 3
Classifier: Programming Language :: Python :: 3.8
Classifier: Programming Language :: Python :: 3.9
Classifier: Programming Language :: Python :: 3.10
Classifier: Programming Language :: Python :: 3.11
Classifier: Typing :: Typed
Requires-Python: >=3.8
Requires-Dist: mido[ports-rtmidi]
Requires-Dist: psygnal>=0.9.0
Provides-Extra: dev
Requires-Dist: black; extra == 'dev'
Requires-Dist: ipython; extra == 'dev'
Requires-Dist: mypy; extra == 'dev'
Requires-Dist: pdbpp; extra == 'dev'
Requires-Dist: rich; extra == 'dev'
Requires-Dist: ruff; extra == 'dev'
Provides-Extra: test
Requires-Dist: pymmcore-plus; extra == 'test'
Requires-Dist: pytest; extra == 'test'
Requires-Dist: pytest-cov; extra == 'test'
Requires-Dist: pyyaml; extra == 'test'
